flightctl/FileWriter.py
flightctl/MainWindow.py
flightctl/Numpad.py
flightctl/SerialCommunicator.py
flightctl/Views.py
flightctl/__init__.py
flightctl/__main__.py
flightctl/cropped-aiaaweblogo-2.png
flightctl-1.0.0.post2.dist-info/METADATA
flightctl-1.0.0.post2.dist-info/WHEEL
flightctl-1.0.0.post2.dist-info/licenses/LICENSE
flightctl-1.0.0.post2.dist-info/RECORD
