Metadata-Version: 2.3
Name: flightctl
Version: 1.0.0.post2
Summary: Rocket Monitoring reimagined
Project-URL: Homepage, https://nathansamuell.github.io/FlightControl/
Project-URL: Issues, https://github.com/nathansamuell/FlightControl/issues
Author-email: Nathan Samuell <nathansamuell@duck.com>
License: MIT License
License-File: LICENSE
Classifier: Development Status :: 2 - Pre-Alpha
Classifier: License :: OSI Approved :: MIT License
Classifier: Operating System :: POSIX :: Linux
Classifier: Programming Language :: Python :: 3
Requires-Python: >=3.8
Requires-Dist: pyserial
Requires-Dist: pytest
Requires-Dist: python-dotenv
